mab/__init__.py
mab/ab.py
mab/annealingsoftmax.py
mab/betats.py
mab/epsilongreedy.py
mab/mab.py
mab/metric.py
mab/randomselect.py
mab/realtime.py
mab/rewards.py
mab/softmax.py
mab/ucb1.py
mab/viz.py
mab_hakuinadvisors-0.3.8.dist-info/WHEEL
mab_hakuinadvisors-0.3.8.dist-info/METADATA
mab_hakuinadvisors-0.3.8.dist-info/RECORD
