Metadata-Version: 2.1
Name: mab-hakuinadvisors
Version: 0.3.8
Summary: Multiarm bandit solutions
License: MIT
Author: Alexey
Author-email: butirev@gmail.com
Requires-Python: >=3.7,<4.0
Classifier: License :: OSI Approved :: MIT License
Classifier: Programming Language :: Python :: 3
Classifier: Programming Language :: Python :: 3.7
Classifier: Programming Language :: Python :: 3.8
